excelunpack/__init__.py
excelunpack/cli.py
excelunpack/extract_attachments.py
excelunpack/utils.py
excel_unpack-0.2.0.dist-info/LICENSE
excel_unpack-0.2.0.dist-info/METADATA
excel_unpack-0.2.0.dist-info/WHEEL
excel_unpack-0.2.0.dist-info/entry_points.txt
excel_unpack-0.2.0.dist-info/top_level.txt
excel_unpack-0.2.0.dist-info/RECORD
