Metadata-Version: 2.2
Name: excel_unpack
Version: 0.2.0
Summary: A tool to extract attachments from Excel (XLSX) files.
Home-page: https://github.com/svk1998/
Author: Shivnand Vishwakarma
Classifier: Programming Language :: Python :: 3
Classifier: License :: OSI Approved :: MIT License
Classifier: Operating System :: OS Independent
License-File: LICENSE
Requires-Dist: olefile
Dynamic: author
Dynamic: classifier
Dynamic: description
Dynamic: description-content-type
Dynamic: home-page
Dynamic: requires-dist
Dynamic: summary
